hdl/p_cntr.v
module p_cntr (clk, rst_n, mode, imm, pc_o);
input clk;
input rst_n;
input [1:0] mode;
input [31:0] imm;
output reg [31:0] pc_o;

parameter STALL=2'b00;
parameter INCR=2'b01;
parameter BRANCH=2'b11;
parameter JALR=2'b10;

reg [31:0] pc_r;

always @(*) begin
	case (mode)
	STALL : pc_r = pc_o;
	INCR : pc_r = pc_o + 4;
	BRANCH : pc_r = pc_o + imm;
	JALR : pc_r = imm;
	endcase
end

always @(posedge clk or negedge rst_n) begin
	if (~rst_n) begin
		pc_o <= 0;
	end else begin
		pc_o <= pc_r;
	end
end

endmodule

hdl/extend32.v
module sigExt ( data_in,
		data_out);

parameter WIDTH = 8;
input [WIDTH-1:0] data_in;
output [31:0] data_out;

//Sign extend data_in to 32 bits
assign data_out = {{(32-WIDTH){data_in[WIDTH-1]}} , data_in};

endmodule

module zeroExt ( data_in,
		data_out);
parameter WIDTH = 8;
input [WIDTH -1 : 0] data_in;
output [31:0] data_out;

//Zero extend data_in to 32 bits
assign data_out = {{(32-WIDTH){1'b0}} , data_in};

endmodule

module extend32 ( data_in,
		sig,
		b_hbar,
		bypass,
		data_out);

input [31:0] data_in;
input sig, b_hbar, bypass;
output reg [31:0] data_out;

wire [31:0] z_extend8_w;
wire [31:0] z_extend16_w;
wire [31:0] s_extend8_w;
wire [31:0] s_extend16_w;

zeroExt #(.WIDTH(8)) zE8(.data_in(data_in[7:0]), .data_out(z_extend8_w));
zeroExt #(.WIDTH(16)) zE16(.data_in(data_in[15:0]), .data_out(z_extend16_w));
sigExt #(.WIDTH(8)) sE8(.data_in(data_in[7:0]), .data_out(s_extend8_w));
sigExt #(.WIDTH(16)) sE16(.data_in(data_in[15:0]), .data_out(s_extend16_w));

always @(*) begin
	if (bypass) begin
		data_out = data_in;
	end else begin
		if (b_hbar) begin
			if (sig) begin
				data_out = s_extend8_w;
			end else begin
				data_out = z_extend8_w;
			end
		end else begin
			if (sig) begin
				data_out = s_extend16_w;
			end else begin
				data_out = z_extend16_w;
			end
		end
	end

end

endmodule

hdl/alu.v
module alu_32 (op1, op2, uop, f7, rst_n, out, zero);

input [31:0] op1;
input [31:0] op2;
input [2:0] uop;
input f7;
input rst_n;
output reg [31:0]out;
output zero;

parameter ADD_SUB=3'b000;
parameter AND=3'b111;
parameter OR=3'b110;
parameter XOR=3'b100;
parameter SL=3'b001;
parameter SR=3'b101;
parameter SLT=3'b010;
parameter SLTU=3'b011;

wire signed [31:0] SR_signed ;
wire [31:0] SR_unsigned ;
assign SR_signed = $signed(op1) >>> (op2 & 32'h0000001f);
assign SR_unsigned = op1 >> (op2 & 32'h0000001f);

always @(*) begin
	if (~rst_n) begin
		out = 32'b0;
	end else begin
	case (uop)
		ADD_SUB : out = f7 ? (op1 - op2) : (op1 + op2);
		AND : out =  op1 & op2;
		OR : out = op1 | op2;
		XOR : out = op1 ^ op2;
		SL : out = op1 << (op2 & 32'h0000001f);
		SR : out = f7 ? SR_signed : SR_unsigned;
		SLT : out = ( $signed(op1) < $signed(op2) );
		SLTU : out = ( op1 < op2 );
	endcase
	end
end

assign zero = ~(| out);


endmodule

hdl/register_file.v
module register_file (rd_data, rs1, rs2, rd, wen, ren, rst_n, o1, o2);
input [31:0] rd_data;
input [4:0] rs1;
input [4:0] rs2;
input [4:0] rd;
input wen, ren, rst_n;

output reg [31:0] o1;
output reg [31:0] o2;

reg [31:0] reg_mem [31:0];

//How to handle simultanous read write ?

//read
always @(*) begin
	if (~rst_n) begin
		o1 = 32'd0;
		o2 = 32'b0;
	end else begin
		if (~ren) begin
			o1 = o1;	//Combo loops ?
			o2 = o2;
		end else begin
			o1 = reg_mem[rs1];
			o2 = reg_mem[rs2];
		end
	end
end

assign reg_mem[0] = 32'd0;

//write back
always @(*) begin
	if (wen & (|rd)) begin
		reg_mem[rd] = rd_data;
	end 
end

endmodule

hdl/ID.v
// Decode the instructions and output all the control signals, this should be the control bus ?
// Control unit will orchestrate


module instr_decode (instr, rst_n, rs1, rs2, rd, alu_uop, opcode, imm, f7, ctrlSig);
input [31:0]instr;
input rst_n;
output [4:0] rs1;
output [4:0] rs2;
output [4:0] rd;
output [2:0] alu_uop;
output [6:0] opcode;
output [31:0] imm;
output f7;

output [15:0] ctrlSig;

assign f7 = instr[30];
assign rs2 = instr[24:20];
assign rs1 = instr[19:15];
assign rd = instr[11:7];
assign alu_uop = instr[14:12];
assign opcode = instr[6:0];


uCode_decode uCode (.alu_uop(alu_uop),
			.opcode(opcode),
			.ctrlSig(ctrlSig));

extract_imm extract_imm_inst (.ctrlSig(ctrlSig),
			.instr(instr),
			.imm(imm),
			.rst_n(rst_n));

endmodule

/*
MSB ---------------- LSB
X, X, X, X, X, X, LUI, AUIPC, JAL, JALR, Branch, STORE, LOAD, Shift-OP, I-Frame, ALU_op
*/

module uCode_decode (alu_uop, opcode, ctrlSig);
input [6:0] opcode;
input [2:0] alu_uop;
output [15:0] ctrlSig;
reg [15:0] ctrlSig_t;
reg [15:0] uCode [127:0];
wire shift_op;

initial
	$readmemb("/home/akhilkushe/Desktop/Projects/CPU_scratch/hdl/uCode.hex", uCode);

always @(*) begin
	ctrlSig_t = uCode[opcode];
end

assign shift_op = ctrlSig_t[0] & (alu_uop == 3'b101 | alu_uop == 3'b001);
assign ctrlSig = (ctrlSig_t | {13'b0000000000000, shift_op,2'b00});

endmodule

// Return sign extended immediate instruction
// TODO, not extracting imm correctly for LOAD/STORE
module extract_imm (ctrlSig, instr, imm, rst_n);
input [15:0]ctrlSig;
input [31:0] instr;
input rst_n;
output reg [31:0] imm;

always @(*) begin
	if (~rst_n) begin
		imm = 32'd0;
	end else begin
		if (ctrlSig[1]) begin // I type
			imm = {{21{instr[31]}}, instr[30:20]}; // If its is I frame, sign extend for immediate
			imm = ctrlSig[2] ? {27'd0, instr[24:20]} : imm; //If shift operation, take unsigned shift amount
		end else if (ctrlSig[4]) begin	//S type
			imm = {{21{instr[31]}}, instr[30:25], instr[11:7]};
		end else if (ctrlSig[5]) begin // B type
			imm = {{20{instr[31]}},instr[7], instr[30:25],instr[11:8],1'b0};
		end else if (ctrlSig[8] | ctrlSig[9]) begin // U type
			imm = {instr[31:12], {12{1'b0}}};
		end else if (ctrlSig[7]) begin // J type
			imm = {{11{instr[31]}}, instr[19:12], instr[20], instr[30:21],1'b0};
		end else begin
			imm = 32'd0;
		end
	end
end

endmodule

hdl/anu_core.v
module anu_core (stall, instr, data_in, rst_n, clk, pc_o, data_out, mem_addr, mem_access_mode);

input stall;
input [31:0] instr;
input [31:0] data_in;
input rst_n;
input clk;

output [31:0] pc_o;
output [31:0] data_out;
output [31:0] mem_addr;
output reg [1:0] mem_access_mode;

wire [4:0] rs1_w;
wire [4:0] rs2_w;
wire [4:0] rd_w;
reg [4:0] rd_r;

wire [31:0] imm_w;
wire [31:0] op1_w;
wire [31:0] op1_pc_w;
wire [31:0] op2_imm_w;
wire [31:0] op2_w;

wire [2:0] uop_w;
reg [2:0] alu_uop_r;
wire f7_w;
reg valid_f7_r;
wire wen_w;
reg wen_r;
reg branch_r;
wire zero_w;

wire [15:0] ctrlSig_w;
wire [31:0] extended_data_in;
wire [31:0] alu_out_w;
wire [31:0] alu_out_imm_w;
wire [31:0] data_wb_w;
reg [31:0] data_wb_r;
wire [31:0] rd_data_w;

reg [1:0] mem_access_mode_r;
wire b_hbar_w, bypass_w, sig_w;

// PC wires
wire pc_mode0_w;
wire pc_mode1_w;
wire [31:0] pc_imm_w;
wire [1:0] pc_mode_w;
wire [31:0] pc_w;

//Alias, fix in ctrl unit
assign alu_op = ctrlSig_w[0];
assign i_frame = ctrlSig_w[1];
assign shift_op = ctrlSig_w[2];
assign ld = ctrlSig_w[3];
assign st = ctrlSig_w[4];
assign branch_op = ctrlSig_w[5];
assign jalr = ctrlSig_w[6];
assign jal = ctrlSig_w[7];
assign auipc = ctrlSig_w[8];
assign lui = ctrlSig_w[9];

initial begin
    $dumpfile("test1.vcd");
    $dumpvars(0);
end



instr_decode instr_decode_inst(.instr(instr), 
				.rst_n(rst_n), 
				.rs1(rs1_w), 
				.rs2(rs2_w), 
				.rd(rd_w), 
				.alu_uop(uop_w), 
				.opcode(), 
				.imm(imm_w), 
				.f7(f7_w), 
				.ctrlSig(ctrlSig_w));

register_file register_file_inst (.rd_data(rd_data_w), 
				.rs1(rs1_w), 
				.rs2(rs2_w), 
				.rd(rd_r), 
				.wen(wen_r), 
				.ren(1'b1), 
				.rst_n(rst_n),
				.o1(op1_w), 
				.o2(op2_w));

//Add to control unit
assign op2_imm_w = (i_frame | st | auipc) ? imm_w : op2_w;        //Operand 2 is imm if its I-frmae (alu/load) or store op
assign wen_w = ~(st | branch_op);		 //If branch or store instruction then dont write back to register
assign op1_pc_w = auipc ? pc_w : op1_w;


always @(*) begin
	if (branch_op) begin // for branch ops, use corresponding alu op
		case (uop_w[2:1])
			2'b00 : begin 
				alu_uop_r = 3'b000; 
				valid_f7_r = 1'b1; // eq -> do sub op
				end
			2'b10 : alu_uop_r = 3'b010; // signed lt -> signed lt -> do 
			2'b11 : alu_uop_r = 3'b011; // unsigned lt
			default : begin	
				alu_uop_r = uop_w; 
				valid_f7_r = 1'b0;
				end
		endcase
	end else if (auipc) begin
		alu_uop_r = 3'b000; //Add PC + Imm
		valid_f7_r = 1'b0;
	end else begin
		alu_uop_r = (ld | st) ? 3'b000 : uop_w;
		valid_f7_r = f7_w & (ctrlSig_w[2]  | ~ctrlSig_w[1]);
	end
end

always @(*) begin
	if (branch_op) begin	// handle branching condition base on type of alu op used (make it readable)
		branch_r = (uop_w[2]^uop_w[0]) ? ~zero_w : zero_w;
		//case ({uop[2], uop[0]})
		//	2'b00 : branch_r = zero_w;
		//	2'b01 : branch_r = ~zero_w;
		//	2'b10 : branch_r = ~zero_w;
		//	2'b11 : branch_r = zero_w;
		//endcase
	end else begin
		branch_r = 1'b0;
	end
end


alu_32 alu_inst (.op1(op1_pc_w), 
		.op2(op2_imm_w), 
		.uop(alu_uop_r), 
		.f7(valid_f7_r), 
		.rst_n(rst_n), 
		.out(alu_out_w),
		.zero(zero_w));

assign mem_addr = alu_out_w;

assign b_hbar_w = ~uop_w[0];
assign bypass_w = uop_w[1];
assign sign_w = uop_w[2];

extend32 ext32 (.data_in(data_in), .data_out(extended_data_in), .b_hbar(b_hbar_w), .bypass(bypass_w), .sig(sig_w));
assign alu_out_imm_w = lui ? imm_w : alu_out_w;
assign data_wb_w = ld ? extended_data_in : alu_out_imm_w;

assign data_out = op2_w;

//Mem access mode
always @(*) begin
	if (st & !ld) begin
		if (bypass_w) begin
			mem_access_mode_r = 2'b11;
		end else begin
			if (b_hbar_w) begin
				mem_access_mode_r = 2'b01;
			end else begin
				mem_access_mode_r = 2'b10;
			end
		end
	end else begin
		mem_access_mode_r = 2'b00;
	end
end

//can be encoded better
assign pc_mode0_w = (branch_r | jal  | ~jalr)&(~stall);
assign pc_mode1_w = (branch_r | jal | jalr)&(~stall);
assign pc_imm_w = pc_mode0_w ? imm_w : alu_out_w;
assign pc_mode_w = {pc_mode1_w, pc_mode0_w};

p_cntr pc (.clk(clk), 
		.rst_n(rst_n),
		.mode(pc_mode_w),
		.imm(pc_imm_w), 
		.pc_o(pc_w));

assign pc_o = pc_w;
assign rd_data_w = (jal | jalr)  ? pc_w + 4 : data_wb_r;

// write back
// Half cycle path, maybe be problem in timing, since ALU is constrained in Half cycle
always @(negedge clk or negedge rst_n) begin
	if (~rst_n) begin
		data_wb_r <= 0;
		rd_r <= 0;
	end else begin
		data_wb_r <= data_wb_w;
		rd_r <= rd_w;
	end
end

// Half cycle Write back logic to reg
always @(posedge clk or negedge clk or negedge rst_n) begin
	if (~rst_n ) begin
		wen_r <= 0;
	end else begin
		wen_r <= clk ? 0 : wen_w;
	end
end

// Half cycle Write back logic to mem
always @(posedge clk or negedge clk or negedge rst_n) begin
	if (~rst_n ) begin
		mem_access_mode <= 2'b00;
	end else begin
		mem_access_mode <= clk ? 2'b00 : mem_access_mode_r;
	end
end

endmodule

/*
* TODO
* 1. ctrl unit
* - Write to use ALU for load operation -> alu_uop and load ctrl signals as output
* - ID is the control unit, add other control signals, like deciding the alu_uop for diff operations in control unit (load branch etc)
* 
* 2. Proper dmem interface
* - Take a protocol, first do single cycle write, then can move to multiple cycle read writes, with stalls
*
* 3. Add branch condition (done verify, add to control unit) (tested only beq)
* eq -> zero = 1 (sub op)
* neq -> zero = 0 (sub op)
* lt/ltu -> zero = 0 (slt/sltu)
* ge/geu -> zero = 1 (slt/sltu)
* - Fix signed and unsigned comparions
* 
* 4. Modification of PC based on op (kind of works)
* 00 -> PC = PC (stall) -> bypass mode
* 01 -> PC = PC + 4 (Next instr, normal op) -> modify adder
* 11 -> PC = PC + IMM (Branch, JAL) -> modify adder
* 10 -> PC = rs1 + IMM (JALR) -> bypass mode
* -Ability to load PC in reg file (for JALR), should happen at write back stage ? yes (done)
* - Do PC+imm in alu, just bypass pc
* 
* 5. LUI, AUIPC, JAL, JALR (done)
*
* 6. Refactor code, make proper modules, load in quartus
*
* 7. Setup verification environment, moderate testing
*
* 8. Single cycle RISC-V done, document it.
*/

verif/coco_tb/basic_test/test1.vcd
$version Generated by VerilatedVcd $end
$timescale 1ps $end
 $scope module $rootio $end
  $var wire 1 # stall $end
  $var wire 32 $ instr [31:0] $end
  $var wire 32 % data_in [31:0] $end
  $var wire 1 & rst_n $end
  $var wire 1 ' clk $end
  $var wire 32 ( pc_o [31:0] $end
  $var wire 32 ) data_out [31:0] $end
  $var wire 32 * mem_addr [31:0] $end
  $var wire 2 + mem_access_mode [1:0] $end
 $upscope $end
 $scope module anu_core $end
  $var wire 1 , stall $end
  $var wire 32 - instr [31:0] $end
  $var wire 32 . data_in [31:0] $end
  $var wire 1 / rst_n $end
  $var wire 1 0 clk $end
  $var wire 32 1 pc_o [31:0] $end
  $var wire 32 2 data_out [31:0] $end
  $var wire 32 3 mem_addr [31:0] $end
  $var wire 2 4 mem_access_mode [1:0] $end
  $var wire 5 5 rs1_w [4:0] $end
  $var wire 5 6 rs2_w [4:0] $end
  $var wire 5 7 rd_w [4:0] $end
  $var wire 5 8 rd_r [4:0] $end
  $var wire 32 9 imm_w [31:0] $end
  $var wire 32 : op1_w [31:0] $end
  $var wire 32 ; op1_pc_w [31:0] $end
  $var wire 32 < op2_imm_w [31:0] $end
  $var wire 32 = op2_w [31:0] $end
  $var wire 3 > uop_w [2:0] $end
  $var wire 3 ? alu_uop_r [2:0] $end
  $var wire 1 @ f7_w $end
  $var wire 1 A valid_f7_r $end
  $var wire 1 B wen_w $end
  $var wire 1 C wen_r $end
  $var wire 1 D branch_r $end
  $var wire 1 E zero_w $end
  $var wire 16 F ctrlSig_w [15:0] $end
  $var wire 32 G extended_data_in [31:0] $end
  $var wire 32 H alu_out_w [31:0] $end
  $var wire 32 I alu_out_imm_w [31:0] $end
  $var wire 32 J data_wb_w [31:0] $end
  $var wire 32 K data_wb_r [31:0] $end
  $var wire 32 L rd_data_w [31:0] $end
  $var wire 2 M mem_access_mode_r [1:0] $end
  $var wire 1 N b_hbar_w $end
  $var wire 1 O bypass_w $end
  $var wire 1 P sig_w $end
  $var wire 1 Q pc_mode0_w $end
  $var wire 1 R pc_mode1_w $end
  $var wire 32 S pc_imm_w [31:0] $end
  $var wire 2 T pc_mode_w [1:0] $end
  $var wire 32 U pc_w [31:0] $end
  $var wire 1 V alu_op $end
  $var wire 1 W i_frame $end
  $var wire 1 X shift_op $end
  $var wire 1 Y ld $end
  $var wire 1 Z st $end
  $var wire 1 [ branch_op $end
  $var wire 1 \ jalr $end
  $var wire 1 ] jal $end
  $var wire 1 ^ auipc $end
  $var wire 1 _ lui $end
  $var wire 1 ` sign_w $end
  $scope module alu_inst $end
   $var wire 32 a op1 [31:0] $end
   $var wire 32 b op2 [31:0] $end
   $var wire 3 c uop [2:0] $end
   $var wire 1 d f7 $end
   $var wire 1 e rst_n $end
   $var wire 32 f out [31:0] $end
   $var wire 1 g zero $end
   $var wire 3 _! ADD_SUB [2:0] $end
   $var wire 3 `! AND [2:0] $end
   $var wire 3 a! OR [2:0] $end
   $var wire 3 b! XOR [2:0] $end
   $var wire 3 c! SL [2:0] $end
   $var wire 3 d! SR [2:0] $end
   $var wire 3 e! SLT [2:0] $end
   $var wire 3 f! SLTU [2:0] $end
   $var wire 32 h SR_signed [31:0] $end
   $var wire 32 i SR_unsigned [31:0] $end
  $upscope $end
  $scope module ext32 $end
   $var wire 32 j data_in [31:0] $end
   $var wire 1 k sig $end
   $var wire 1 l b_hbar $end
   $var wire 1 m bypass $end
   $var wire 32 n data_out [31:0] $end
   $var wire 32 o z_extend8_w [31:0] $end
   $var wire 32 p z_extend16_w [31:0] $end
   $var wire 32 q s_extend8_w [31:0] $end
   $var wire 32 r s_extend16_w [31:0] $end
   $scope module sE16 $end
    $var wire 32 g! WIDTH [31:0] $end
    $var wire 16 s data_in [15:0] $end
    $var wire 32 t data_out [31:0] $end
   $upscope $end
   $scope module sE8 $end
    $var wire 32 h! WIDTH [31:0] $end
    $var wire 8 u data_in [7:0] $end
    $var wire 32 v data_out [31:0] $end
   $upscope $end
   $scope module zE16 $end
    $var wire 32 g! WIDTH [31:0] $end
    $var wire 16 w data_in [15:0] $end
    $var wire 32 x data_out [31:0] $end
   $upscope $end
   $scope module zE8 $end
    $var wire 32 h! WIDTH [31:0] $end
    $var wire 8 y data_in [7:0] $end
    $var wire 32 z data_out [31:0] $end
   $upscope $end
  $upscope $end
  $scope module instr_decode_inst $end
   $var wire 32 { instr [31:0] $end
   $var wire 1 | rst_n $end
   $var wire 5 } rs1 [4:0] $end
   $var wire 5 ~ rs2 [4:0] $end
   $var wire 5 !! rd [4:0] $end
   $var wire 3 "! alu_uop [2:0] $end
   $var wire 7 #! opcode [6:0] $end
   $var wire 32 $! imm [31:0] $end
   $var wire 1 %! f7 $end
   $var wire 16 &! ctrlSig [15:0] $end
   $scope module extract_imm_inst $end
    $var wire 16 '! ctrlSig [15:0] $end
    $var wire 32 (! instr [31:0] $end
    $var wire 1 )! rst_n $end
    $var wire 32 *! imm [31:0] $end
   $upscope $end
   $scope module uCode $end
    $var wire 7 +! opcode [6:0] $end
    $var wire 3 ,! alu_uop [2:0] $end
    $var wire 16 -! ctrlSig [15:0] $end
    $var wire 16 .! ctrlSig_t [15:0] $end
    $var wire 1 /! shift_op $end
   $upscope $end
  $upscope $end
  $scope module pc $end
   $var wire 1 0! clk $end
   $var wire 1 1! rst_n $end
   $var wire 2 2! mode [1:0] $end
   $var wire 32 3! imm [31:0] $end
   $var wire 32 4! pc_o [31:0] $end
   $var wire 2 i! STALL [1:0] $end
   $var wire 2 j! INCR [1:0] $end
   $var wire 2 k! BRANCH [1:0] $end
   $var wire 2 l! JALR [1:0] $end
   $var wire 32 5! pc_r [31:0] $end
  $upscope $end
  $scope module register_file_inst $end
   $var wire 32 6! rd_data [31:0] $end
   $var wire 5 7! rs1 [4:0] $end
   $var wire 5 8! rs2 [4:0] $end
   $var wire 5 9! rd [4:0] $end
   $var wire 1 :! wen $end
   $var wire 1 ;! ren $end
   $var wire 1 <! rst_n $end
   $var wire 32 =! o1 [31:0] $end
   $var wire 32 >! o2 [31:0] $end
   $var wire 32 ?! reg_mem[0] [31:0] $end
   $var wire 32 @! reg_mem[1] [31:0] $end
   $var wire 32 A! reg_mem[2] [31:0] $end
   $var wire 32 B! reg_mem[3] [31:0] $end
   $var wire 32 C! reg_mem[4] [31:0] $end
   $var wire 32 D! reg_mem[5] [31:0] $end
   $var wire 32 E! reg_mem[6] [31:0] $end
   $var wire 32 F! reg_mem[7] [31:0] $end
   $var wire 32 G! reg_mem[8] [31:0] $end
   $var wire 32 H! reg_mem[9] [31:0] $end
   $var wire 32 I! reg_mem[10] [31:0] $end
   $var wire 32 J! reg_mem[11] [31:0] $end
   $var wire 32 K! reg_mem[12] [31:0] $end
   $var wire 32 L! reg_mem[13] [31:0] $end
   $var wire 32 M! reg_mem[14] [31:0] $end
   $var wire 32 N! reg_mem[15] [31:0] $end
   $var wire 32 O! reg_mem[16] [31:0] $end
   $var wire 32 P! reg_mem[17] [31:0] $end
   $var wire 32 Q! reg_mem[18] [31:0] $end
   $var wire 32 R! reg_mem[19] [31:0] $end
   $var wire 32 S! reg_mem[20] [31:0] $end
   $var wire 32 T! reg_mem[21] [31:0] $end
   $var wire 32 U! reg_mem[22] [31:0] $end
   $var wire 32 V! reg_mem[23] [31:0] $end
   $var wire 32 W! reg_mem[24] [31:0] $end
   $var wire 32 X! reg_mem[25] [31:0] $end
   $var wire 32 Y! reg_mem[26] [31:0] $end
   $var wire 32 Z! reg_mem[27] [31:0] $end
   $var wire 32 [! reg_mem[28] [31:0] $end
   $var wire 32 \! reg_mem[29] [31:0] $end
   $var wire 32 ]! reg_mem[30] [31:0] $end
   $var wire 32 ^! reg_mem[31] [31:0] $end
  $upscope $end
 $upscope $end
$enddefinitions $end


#0
0#
b00000000000000000000000000000000 $
b00000000000000000000000000000000 %
1&
0'
b00000000000000000000000000000000 (
b00000000000000000000000000000000 )
b00000000000000000000000000000000 *
b00 +
0,
b00000000000000000000000000000000 -
b00000000000000000000000000000000 .
1/
00
b00000000000000000000000000000000 1
b00000000000000000000000000000000 2
b00000000000000000000000000000000 3
b00 4
b00000 5
b00000 6
b00000 7
b00000 8
b00000000000000000000000000000000 9
b00000000000000000000000000000000 :
b00000000000000000000000000000000 ;
b00000000000000000000000000000000 <
b00000000000000000000000000000000 =
b000 >
b000 ?
0@
0A
1B
0C
0D
1E
b0000000000000000 F
b00000000000000000000000000000000 G
b00000000000000000000000000000000 H
b00000000000000000000000000000000 I
b00000000000000000000000000000000 J
b00000000000000000000000000000000 K
b00000000000000000000000000000000 L
b00 M
1N
0O
0P
1Q
0R
b00000000000000000000000000000000 S
b01 T
b00000000000000000000000000000000 U
0V
0W
0X
0Y
0Z
0[
0\
0]
0^
0_
0`
b00000000000000000000000000000000 a
b00000000000000000000000000000000 b
b000 c
0d
1e
b00000000000000000000000000000000 f
1g
b00000000000000000000000000000000 h
b00000000000000000000000000000000 i
b00000000000000000000000000000000 j
0k
1l
0m
b00000000000000000000000000000000 n
b00000000000000000000000000000000 o
b00000000000000000000000000000000 p
b00000000000000000000000000000000 q
b00000000000000000000000000000000 r
b0000000000000000 s
b00000000000000000000000000000000 t
b00000000 u
b00000000000000000000000000000000 v
b0000000000000000 w
b00000000000000000000000000000000 x
b00000000 y
b00000000000000000000000000000000 z
b00000000000000000000000000000000 {
1|
b00000 }
b00000 ~
b00000 !!
b000 "!
b0000000 #!
b00000000000000000000000000000000 $!
0%!
b0000000000000000 &!
b0000000000000000 '!
b00000000000000000000000000000000 (!
1)!
b00000000000000000000000000000000 *!
b0000000 +!
b000 ,!
b0000000000000000 -!
b0000000000000000 .!
0/!
00!
11!
b01 2!
b00000000000000000000000000000000 3!
b00000000000000000000000000000000 4!
b00000000000000000000000000000100 5!
b00000000000000000000000000000000 6!
b00000 7!
b00000 8!
b00000 9!
0:!
1;!
1<!
b00000000000000000000000000000000 =!
b00000000000000000000000000000000 >!
b00000000000000000000000000000000 ?!
b00000000000000000000000000000000 @!
b00000000000000000000000000000000 A!
b00000000000000000000000000000000 B!
b00000000000000000000000000000000 C!
b00000000000000000000000000000000 D!
b00000000000000000000000000000000 E!
b00000000000000000000000000000000 F!
b00000000000000000000000000000000 G!
b00000000000000000000000000000000 H!
b00000000000000000000000000000000 I!
b00000000000000000000000000000000 J!
b00000000000000000000000000000000 K!
b00000000000000000000000000000000 L!
b00000000000000000000000000000000 M!
b00000000000000000000000000000000 N!
b00000000000000000000000000000000 O!
b00000000000000000000000000000000 P!
b00000000000000000000000000000000 Q!
b00000000000000000000000000000000 R!
b00000000000000000000000000000000 S!
b00000000000000000000000000000000 T!
b00000000000000000000000000000000 U!
b00000000000000000000000000000000 V!
b00000000000000000000000000000000 W!
b00000000000000000000000000000000 X!
b00000000000000000000000000000000 Y!
b00000000000000000000000000000000 Z!
b00000000000000000000000000000000 [!
b00000000000000000000000000000000 \!
b00000000000000000000000000000000 ]!
b00000000000000000000000000000000 ^!
b000 _!
b111 `!
b110 a!
b100 b!
b001 c!
b101 d!
b010 e!
b011 f!
b00000000000000000000000000010000 g!
b00000000000000000000000000001000 h!
b00 i!
b01 j!
b11 k!
b10 l!
#500
0&
0/
0e
0|
0)!
01!
0<!
#1000
1'
10
10!
#1500
b00000000001000110101101110110011 $
1&
b00000000001000110101101110110011 -
1/
b00110 5
b00010 6
b10111 7
b101 >
b101 ?
b0000000000000101 F
0N
1V
1X
1`
b101 c
1e
0l
b00000000001000110101101110110011 {
1|
b00110 }
b00010 ~
b10111 !!
b101 "!
b0110011 #!
b0000000000000101 &!
b0000000000000101 '!
b00000000001000110101101110110011 (!
1)!
b0110011 +!
b101 ,!
b0000000000000101 -!
b0000000000000001 .!
1/!
11!
b00110 7!
b00010 8!
1<!
#2000
0'
00
b10111 8
1C
00!
b10111 9!
1:!
#3000
1'
b00000000000000000000000000000100 (
10
b00000000000000000000000000000100 1
0C
b00000000000000000000000000000100 U
10!
b00000000000000000000000000000100 4!
b00000000000000000000000000001000 5!
0:!
#4000
b00000000001110101001001100110011 $
0'
b00000000001110101001001100110011 -
00
b10101 5
b00011 6
b00110 7
b001 >
b001 ?
1C
0`
b001 c
b00000000001110101001001100110011 {
b10101 }
b00011 ~
b00110 !!
b001 "!
b00000000001110101001001100110011 (!
b001 ,!
00!
b10101 7!
b00011 8!
1:!
#5000
1'
b00000000000000000000000000001000 (
10
b00000000000000000000000000001000 1
0C
b00000000000000000000000000001000 U
10!
b00000000000000000000000000001000 4!
b00000000000000000000000000001100 5!
0:!
#6000
b01101110011001110100101100010011 $
0'
b00000000000000000000011011100110 *
b01101110011001110100101100010011 -
00
b00000000000000000000011011100110 3
b01110 5
b00110 6
b10110 7
b00110 8
b00000000000000000000011011100110 9
b00000000000000000000011011100110 <
b100 >
b100 ?
1@
1C
0E
b0000000000000011 F
b00000000000000000000011011100110 H
b00000000000000000000011011100110 I
b00000000000000000000011011100110 J
1N
b00000000000000000000011011100110 S
1W
0X
1`
b00000000000000000000011011100110 b
b100 c
b00000000000000000000011011100110 f
0g
1l
b01101110011001110100101100010011 {
b01110 }
b00110 ~
b10110 !!
b100 "!
b0010011 #!
b00000000000000000000011011100110 $!
1%!
b0000000000000011 &!
b0000000000000011 '!
b01101110011001110100101100010011 (!
b00000000000000000000011011100110 *!
b0010011 +!
b100 ,!
b0000000000000011 -!
b0000000000000011 .!
0/!
00!
b00000000000000000000011011100110 3!
b01110 7!
b00110 8!
b00110 9!
1:!
#7000
1'
b00000000000000000000000000001100 (
10
b00000000000000000000000000001100 1
0C
b00000000000000000000000000001100 U
10!
b00000000000000000000000000001100 4!
b00000000000000000000000000010000 5!
0:!
#8000
b00000001001100110100010100110011 $
0'
b00000000000000000000000000000000 *
b00000001001100110100010100110011 -
00
b00000000000000000000000000000000 3
b00110 5
b10011 6
b01010 7
b10110 8
b00000000000000000000000000000000 9
b00000000000000000000000000000000 <
0@
1C
1E
b0000000000000001 F
b00000000000000000000000000000000 H
b00000000000000000000000000000000 I
b00000000000000000000000000000000 J
b00000000000000000000011011100110 K
b00000000000000000000011011100110 L
b00000000000000000000000000000000 S
0W
b00000000000000000000000000000000 b
b00000000000000000000000000000000 f
1g
b00000001001100110100010100110011 {
b00110 }
b10011 ~
b01010 !!
b0110011 #!
b00000000000000000000000000000000 $!
0%!
b0000000000000001 &!
b0000000000000001 '!
b00000001001100110100010100110011 (!
b00000000000000000000000000000000 *!
b0110011 +!
b0000000000000001 -!
b0000000000000001 .!
00!
b00000000000000000000000000000000 3!
b00000000000000000000011011100110 6!
b00110 7!
b10011 8!
b10110 9!
1:!
b00000000000000000000011011100110 U!
#9000
1'
b00000000000000000000000000010000 (
10
b00000000000000000000000000010000 1
0C
b00000000000000000000000000010000 U
10!
b00000000000000000000000000010000 4!
b00000000000000000000000000010100 5!
0:!
#10000
b00000001000001011011111010110011 $
0'
b00000001000001011011111010110011 -
00
b01011 5
b10000 6
b11101 7
b01010 8
b011 >
b011 ?
1C
b00000000000000000000000000000000 K
b00000000000000000000000000000000 L
0N
1O
0`
b011 c
0l
1m
b00000001000001011011111010110011 {
b01011 }
b10000 ~
b11101 !!
b011 "!
b00000001000001011011111010110011 (!
b011 ,!
00!
b00000000000000000000000000000000 6!
b01011 7!
b10000 8!
b01010 9!
1:!
#11000
1'
b00000000000000000000000000010100 (
10
b00000000000000000000000000010100 1
0C
b00000000000000000000000000010100 U
10!
b00000000000000000000000000010100 4!
b00000000000000000000000000011000 5!
0:!
#12000
b00000001010010010001001010010011 $
0'
b00000001010010010001001010010011 -
00
b10010 5
b10100 6
b00101 7
b11101 8
b00000000000000000000000000010100 9
b00000000000000000000000000010100 <
b001 >
b001 ?
1C
b0000000000000111 F
0O
b00000000000000000000000000010100 S
1W
1X
b00000000000000000000000000010100 b
b001 c
0m
b00000001010010010001001010010011 {
b10010 }
b10100 ~
b00101 !!
b001 "!
b0010011 #!
b00000000000000000000000000010100 $!
b0000000000000111 &!
b0000000000000111 '!
b00000001010010010001001010010011 (!
b00000000000000000000000000010100 *!
b0010011 +!
b001 ,!
b0000000000000111 -!
b0000000000000011 .!
1/!
00!
b00000000000000000000000000010100 3!
b10010 7!
b10100 8!
b11101 9!
1:!
#13000
1'
b00000000000000000000000000011000 (
10
b00000000000000000000000000011000 1
0C
b00000000000000000000000000011000 U
10!
b00000000000000000000000000011000 4!
b00000000000000000000000000011100 5!
0:!
